MANIFEST.in
bower.json
index.html
setup.py
AnalysisProjectDependencies.egg-info/PKG-INFO
AnalysisProjectDependencies.egg-info/SOURCES.txt
AnalysisProjectDependencies.egg-info/dependency_links.txt
AnalysisProjectDependencies.egg-info/not-zip-safe
AnalysisProjectDependencies.egg-info/requires.txt
AnalysisProjectDependencies.egg-info/top_level.txt
analysis_project_dependencies/__init__.py
analysis_project_dependencies/analysis_file.py
analysis_project_dependencies/analysis_module.py
analysis_project_dependencies/analysis_test.py
analysis_project_dependencies/entrance_generate.py
analysis_project_dependencies/modules.py
bower_components/cytoscape/.bower.json
bower_components/cytoscape/.eslintrc.json
bower_components/cytoscape/.gitignore
bower_components/cytoscape/.jscsrc
bower_components/cytoscape/.npmignore
bower_components/cytoscape/.travis.yml
bower_components/cytoscape/ISSUE_TEMPLATE.md
bower_components/cytoscape/LICENSE
bower_components/cytoscape/README.md
bower_components/cytoscape/bower.json
bower_components/cytoscape/benchmark/a-star.js
bower_components/cytoscape/benchmark/add-remove.js
bower_components/cytoscape/benchmark/add.js
bower_components/cytoscape/benchmark/all-are-neighbors.js
bower_components/cytoscape/benchmark/all-are.js
bower_components/cytoscape/benchmark/any-same.js
bower_components/cytoscape/benchmark/bellman-ford.js
bower_components/cytoscape/benchmark/betweenness-centrality.js
bower_components/cytoscape/benchmark/bfs.js
bower_components/cytoscape/benchmark/closeness-centrality.js
bower_components/cytoscape/benchmark/collection-creation.js
bower_components/cytoscape/benchmark/contains.js
bower_components/cytoscape/benchmark/degree-centrality.js
bower_components/cytoscape/benchmark/dfs.js
bower_components/cytoscape/benchmark/dijkstra.js
bower_components/cytoscape/benchmark/floyd-warshall.js
bower_components/cytoscape/benchmark/id-selector.js
bower_components/cytoscape/benchmark/init.js
bower_components/cytoscape/benchmark/is.js
bower_components/cytoscape/benchmark/kerger-stein.js
bower_components/cytoscape/benchmark/kruskal.js
bower_components/cytoscape/benchmark/old-version.json
bower_components/cytoscape/benchmark/page-rank.js
bower_components/cytoscape/benchmark/same.js
bower_components/cytoscape/benchmark/graphs/abcde.json
