Metadata-Version: 1.1
Name: AnalysisProjectDependencies
Version: 0.1
Summary: Analysis project dependence(support java project)
Home-page: https://github.com/Kyson/AnalysisProjectDependencies
Author: Kyson
Author-email: kysonchao@gmail.com
License: BSD
Platform: any
Classifier: Programming Language :: Python :: 2.7
Classifier: License :: OSI Approved :: BSD License
